lumigator_sdk/__init__.py
lumigator_sdk/client.py
lumigator_sdk/completions.py
lumigator_sdk/experiments.py
lumigator_sdk/health.py
lumigator_sdk/jobs.py
lumigator_sdk/lm_datasets.py
lumigator_sdk/lumigator.py
lumigator_sdk/models.py
lumigator_sdk/strict_schemas.py
lumigator_sdk-0.0.2.dist-info/METADATA
lumigator_sdk-0.0.2.dist-info/WHEEL
lumigator_sdk-0.0.2.dist-info/RECORD
