Metadata-Version: 2.4
Name: lumigator-sdk
Version: 0.0.2
Summary: Lumigator SDK using the REST API
Requires-Python: >=3.11
Requires-Dist: loguru==0.7.2
Requires-Dist: lumigator-schemas==0.0.2
Requires-Dist: requests<3,>=2
